{"./":{"url":"./","title":"Index","keywords":"","body":"Shouyin-Doc 欢迎使用 首尹Bot。Do u know how to shouyin? 这里是她的使用文档 贡献 欢迎Bot用户帮助我补充指令使用方法 关于 使用Gitbook生成 "},"commands/slash/":{"url":"commands/slash/","title":"Slash Commands","keywords":"","body":"\"/\" Commands 简介 \"/\"作为常用的命令前缀 在首尹的指令前缀中也有极高的占比 提醒 \"/\" Command一般会需要下级参数 举例： > /screeps rs shard3/W25S11 返回： RoomSnapshot.png "},"commands/slash/screeps.html":{"url":"commands/slash/screeps.html","title":"/screeps","keywords":"","body":"/screeps 指令 简介 Screeps游戏的相关操作 非常好玩赶紧给👴去玩 权限 普通用户组及以上 二级指令 roomStatus(rs) - 用于生成房间快照 /Screep rs shard3/W25S11 参数： shard名/房号 info - 用于获取某一Object的信息 /screeps info shard3/W25S11 storage 参数： shard名/房号 ObjectID / Object类型（忽视大小写） 支持的类型： ['storage','terminal','factory','controller','mineral', 'powerspawn','nuker','observer','powerbank','deposit'] "},"commands/slash/image.html":{"url":"commands/slash/image.html","title":"/image","keywords":"","body":"/image 指令 简介 图片相关操作 别称 此指令可缩写为：/img 权限 普通用户组及以上 二级指令 bin - 将图片二值化（黑白化） /image bin 无参数 附加消息： 待处理的图片 exif - 获取图片的EXIF信息 /image exif 无参数 附加消息: 待处理的图片 size - 获取图片尺寸（单位像素） /image size 无参数 附加消息： 待处理的图片 resize - 返回规定尺寸修改后的图片 /image resize 60*60 参数： 目标尺寸 支持的分割方式： ['x', 'X', '*'] 附加消息： 待处理的图片 gaussianblur(gs) - 对图片进行高斯模糊 /image gs 60 参数： 模糊半径 附加消息： 待处理的图片 "},"commands/dot/":{"url":"commands/dot/","title":"Dot Commands","keywords":"","body":"\".\" Commands 简介 \".\"Command大部分为短指令 相比于以\"/\"开头显得更加轻巧 提醒 \".\" Command一般需要at人使用 需要注意的是，at一般与指令直接相连 举例： > .avatar@Tracer 返回： Tracer-Avatar.png "},"commands/dot/avatar.html":{"url":"commands/dot/avatar.html","title":".avatar","keywords":"","body":".avatar 指令 简介 获取所at用户的QQ头像 .avatar@Stapx_Steve 参数： 标准QQ at 消息 权限 普通用户组及以上 "},"commands/dot/jrrp.html":{"url":"commands/dot/jrrp.html","title":".jrrp","keywords":"","body":".jrrp 指令 简介 获取今日人品 .jrrp 无参数 权限 普通用户组及以上 "},"commands/other/":{"url":"commands/other/","title":"Others","keywords":"","body":"Special Commands 简介 此类型指令无特殊前缀 适用于在群组内自动触发 举例： > ck! 返回： ${user_id}! "},"commands/other/SPFG.html":{"url":"commands/other/SPFG.html","title":"ck!","keywords":"","body":"ck! 指令 简介 一个标准的 SPFG 通讯协议指令 返回一条问候消息 ${user_id}! ，或者是来自动态软链接的内容 （经常被 SS 用于查看首尹有没有宕机） ck！ ck! 无参数 权限 普通用户组及以上 "}}